persistent_ssh_agent/__init__.py
persistent_ssh_agent/__version__.py
persistent_ssh_agent/auth_strategy.py
persistent_ssh_agent/cli.py
persistent_ssh_agent/config.py
persistent_ssh_agent/constants.py
persistent_ssh_agent/core.py
persistent_ssh_agent/git.py
persistent_ssh_agent/ssh_config_parser.py
persistent_ssh_agent/ssh_key_manager.py
persistent_ssh_agent/utils.py
persistent_ssh_agent-0.12.0.dist-info/LICENSE
persistent_ssh_agent-0.12.0.dist-info/METADATA
persistent_ssh_agent-0.12.0.dist-info/WHEEL
persistent_ssh_agent-0.12.0.dist-info/entry_points.txt
persistent_ssh_agent-0.12.0.dist-info/RECORD
