Metadata-Version: 2.3
Name: persistent-ssh-agent
Version: 0.12.0
Summary: A Python library for persistent SSH agent management with automatic key handling, focusing on Windows compatibility and seamless Git integration.
License: MIT
Author: longhao
Author-email: hal.long@outlook.com
Requires-Python: >=3.8,<4.0
Classifier: License :: OSI Approved :: MIT License
Classifier: Programming Language :: Python :: 3
Classifier: Programming Language :: Python :: 3.8
Classifier: Programming Language :: Python :: 3.9
Classifier: Programming Language :: Python :: 3.10
Classifier: Programming Language :: Python :: 3.11
Classifier: Programming Language :: Python :: 3.12
Classifier: Programming Language :: Python :: 3.13
Requires-Dist: click (>=8.1.0)
Requires-Dist: cryptography (>=45.0.0)
Requires-Dist: loguru (>=0.7.0)
